pytest_nlcov/__init__.py
pytest_nlcov/cov.py
pytest_nlcov/data.py
pytest_nlcov/format.py
pytest_nlcov/git.py
pytest_nlcov-0.4.0.dist-info/METADATA
pytest_nlcov-0.4.0.dist-info/WHEEL
pytest_nlcov-0.4.0.dist-info/entry_points.txt
pytest_nlcov-0.4.0.dist-info/RECORD
