Metadata-Version: 2.1
Name: pytest_nlcov
Version: 0.4.0
Summary: Pytest plugin to get the coverage of the new lines (based on git diff) only
Home-page: https://github.com/mrijken/pytest_nlcov
License: MIT
Author: Marc Rijken
Author-email: marc@rijken.org
Requires-Python: >=3.8,<4.0
Classifier: License :: OSI Approved :: MIT License
Classifier: Programming Language :: Python :: 3
Classifier: Programming Language :: Python :: 3.8
Classifier: Programming Language :: Python :: 3.9
Classifier: Programming Language :: Python :: 3.10
Classifier: Programming Language :: Python :: 3.11
Classifier: Programming Language :: Python :: 3.12
Requires-Dist: GitPython (>=3.1.17)
Requires-Dist: coverage (>=7.6.1)
Requires-Dist: pytest-cov (>=5.0.0)
Requires-Dist: typer (>=0.12.3)
Requires-Dist: unidiff (>=0.7.5)
Project-URL: Repository, https://github.com/mrijken/pytest_nlcov
